dogesetup/__init__.py
dogesetup/__main__.py
dogesetup/heroku.py
dogesetup/keys.py
dogesetup/language.py
dogesetup/session.py
dogesetup/languages/DOGE-EN.json.py
dogesetup/languages/DOGE-TR.json.py
dogesetup/languages/__init__.py
DogeSetup-1.2.3.dist-info/LICENSE
DogeSetup-1.2.3.dist-info/METADATA
DogeSetup-1.2.3.dist-info/WHEEL
DogeSetup-1.2.3.dist-info/top_level.txt
DogeSetup-1.2.3.dist-info/RECORD
