Metadata-Version: 2.1
Name: DogeSetup
Version: 1.2.3
Summary: A secure and powerful Python-Telethon based library for Doge UserBot.
Home-page: https://github.com/DOG-E/DogeUserBot
Author: DOG-E
Author-email: DogeUserBot@gmail.com
License: GNU AFFERO GENERAL PUBLIC LICENSE (v3)
Platform: UNKNOWN
Classifier: Programming Language :: Python :: 3
Classifier: Programming Language :: Python :: 3.6
Classifier: Programming Language :: Python :: 3.7
Classifier: Programming Language :: Python :: 3.8
Classifier: Programming Language :: Python :: 3.9
Classifier: License :: OSI Approved :: GNU General Public License v3 (GPLv3)
Classifier: Operating System :: OS Independent
Requires-Python: >=3.6
License-File: LICENSE
Requires-Dist: gitpython
Requires-Dist: herokum
Requires-Dist: requests
Requires-Dist: rich
Requires-Dist: telethon
